["{\"Plan\": {\"Node Type\": \"Other\", \"Node Type ID\": \"42\", \"Total Cost\": 396978.48875, \"Plan Rows\": 1.0, \"Plans\": [{\"Node Type\": \"Other\", \"Node Type ID\": \"45\", \"Total Cost\": 396978.47375, \"Plan Rows\": 2.0, \"Plans\": [{\"Node Type\": \"Other\", \"Node Type ID\": \"42\", \"Total Cost\": 395978.27375, \"Plan Rows\": 1.0, \"Plans\": [{\"Node Type\": \"Hash Join\", \"Node Type ID\": \"38\", \"Total Cost\": 395845.88625, \"Plan Rows\": 52951.0, \"Plans\": [{\"Node Type\": \"Seq Scan\", \"Node Type ID\": \"19\", \"Relation Name\": \"movie_info\", \"Total Cost\": 283223.333333, \"Plan Rows\": 935632.0}, {\"Node Type\": \"Other\", \"Node Type ID\": \"47\", \"Total Cost\": 108148.077917, \"Plan Rows\": 59618.0, \"Plans\": [{\"Node Type\": \"Hash Join\", \"Node Type ID\": \"38\", \"Total Cost\": 108148.077917, \"Plan Rows\": 59618.0, \"Plans\": [{\"Node Type\": \"Seq Scan\", \"Node Type ID\": \"19\", \"Relation Name\": \"movie_keyword\", \"Total Cost\": 48016.135417, \"Plan Rows\": 1216690.0}, {\"Node Type\": \"Other\", \"Node Type ID\": \"47\", \"Total Cost\": 56292.90625, \"Plan Rows\": 51618.0, \"Plans\": [{\"Node Type\": \"Seq Scan\", \"Node Type ID\": \"19\", \"Relation Name\": \"title\", \"Total Cost\": 56292.90625, \"Plan Rows\": 51618.0}]}]}]}]}]}]}]}, \"Buffers\": {\"title\": 13198, \"movie_companies\": 1567, \"cast_info_pkey\": 1, \"title_pkey\": 78, \"movie_keyword\": 473, \"movie_companies_pkey\": 1, \"cast_info\": 675, \"movie_info\": 130, \"movie_info_idx_pkey\": 1, \"movie_info_idx\": 96, \"movie_info_pkey\": 1, \"movie_keyword_pkey\": 1}}", 1416.867187]