["{\"Plan\": {\"Node Type\": \"Other\", \"Node Type ID\": \"42\", \"Total Cost\": 49494.347917, \"Plan Rows\": 1.0, \"Plans\": [{\"Node Type\": \"Other\", \"Node Type ID\": \"45\", \"Total Cost\": 49494.332917, \"Plan Rows\": 2.0, \"Plans\": [{\"Node Type\": \"Other\", \"Node Type ID\": \"42\", \"Total Cost\": 48494.132917, \"Plan Rows\": 1.0, \"Plans\": [{\"Node Type\": \"Seq Scan\", \"Node Type ID\": \"19\", \"Relation Name\": \"movie_keyword\", \"Total Cost\": 48016.135417, \"Plan Rows\": 191195.0}]}]}]}, \"Buffers\": {\"movie_info_idx\": 384, \"title\": 14500, \"title_pkey\": 113, \"movie_companies\": 348, \"movie_info\": 437, \"movie_keyword\": 462, \"movie_companies_pkey\": 1, \"cast_info_pkey\": 1, \"movie_keyword_pkey\": 1, \"movie_info_pkey\": 1, \"movie_info_idx_pkey\": 1}}", 186.879746]