["{\"Plan\": {\"Node Type\": \"Other\", \"Node Type ID\": \"42\", \"Total Cost\": 481572.434931, \"Plan Rows\": 1.0, \"Plans\": [{\"Node Type\": \"Other\", \"Node Type ID\": \"45\", \"Total Cost\": 481572.419931, \"Plan Rows\": 2.0, \"Plans\": [{\"Node Type\": \"Other\", \"Node Type ID\": \"42\", \"Total Cost\": 480572.219931, \"Plan Rows\": 1.0, \"Plans\": [{\"Node Type\": \"Nested Loop\", \"Node Type ID\": \"36\", \"Total Cost\": 480571.794931, \"Plan Rows\": 166.0, \"Plans\": [{\"Node Type\": \"Seq Scan\", \"Node Type ID\": \"19\", \"Relation Name\": \"cast_info\", \"Total Cost\": 479184.525, \"Plan Rows\": 166.0}, {\"Node Type\": \"Index Only Scan\", \"Node Type ID\": \"22\", \"Relation Name\": \"title\", \"Total Cost\": 8.357048, \"Plan Rows\": 1.0}]}]}]}]}, \"Buffers\": {\"title\": 12959, \"movie_keyword\": 482, \"title_pkey\": 1952, \"movie_info\": 192, \"movie_info_idx_pkey\": 1, \"movie_info_idx\": 192, \"movie_companies_pkey\": 1, \"movie_companies\": 153, \"cast_info_pkey\": 1, \"cast_info\": 288, \"movie_keyword_pkey\": 1, \"movie_info_pkey\": 1}}", 1793.42933]