["{\"Plan\": {\"Node Type\": \"Other\", \"Node Type ID\": \"42\", \"Total Cost\": 787741.340458, \"Plan Rows\": 1.0, \"Plans\": [{\"Node Type\": \"Other\", \"Node Type ID\": \"45\", \"Total Cost\": 787741.325458, \"Plan Rows\": 2.0, \"Plans\": [{\"Node Type\": \"Other\", \"Node Type ID\": \"42\", \"Total Cost\": 786741.125458, \"Plan Rows\": 1.0, \"Plans\": [{\"Node Type\": \"Hash Join\", \"Node Type ID\": \"38\", \"Total Cost\": 763042.277958, \"Plan Rows\": 9479535.0, \"Plans\": [{\"Node Type\": \"Seq Scan\", \"Node Type ID\": \"19\", \"Relation Name\": \"cast_info\", \"Total Cost\": 479184.525, \"Plan Rows\": 9185640.0}, {\"Node Type\": \"Other\", \"Node Type ID\": \"47\", \"Total Cost\": 116066.330458, \"Plan Rows\": 1087137.0, \"Plans\": [{\"Node Type\": \"Hash Join\", \"Node Type ID\": \"38\", \"Total Cost\": 116066.330458, \"Plan Rows\": 1087137.0, \"Plans\": [{\"Node Type\": \"Seq Scan\", \"Node Type ID\": \"19\", \"Relation Name\": \"movie_companies\", \"Total Cost\": 29661.370833, \"Plan Rows\": 1087137.0}, {\"Node Type\": \"Other\", \"Node Type ID\": \"47\", \"Total Cost\": 53659.325, \"Plan Rows\": 1053432.0, \"Plans\": [{\"Node Type\": \"Seq Scan\", \"Node Type ID\": \"19\", \"Relation Name\": \"title\", \"Total Cost\": 53659.325, \"Plan Rows\": 1053432.0}]}]}]}]}]}]}]}, \"Buffers\": {\"title\": 13531, \"title_pkey\": 620, \"movie_keyword\": 1255, \"cast_info\": 108, \"cast_info_pkey\": 1, \"movie_info_idx\": 1, \"movie_info\": 215, \"movie_companies\": 503, \"movie_info_pkey\": 1, \"movie_info_idx_pkey\": 1, \"movie_keyword_pkey\": 1, \"movie_companies_pkey\": 1}}", 7530.803756]