["{\"Plan\": {\"Node Type\": \"Other\", \"Node Type ID\": \"42\", \"Total Cost\": 51983.615417, \"Plan Rows\": 1.0, \"Plans\": [{\"Node Type\": \"Other\", \"Node Type ID\": \"45\", \"Total Cost\": 51983.600417, \"Plan Rows\": 2.0, \"Plans\": [{\"Node Type\": \"Other\", \"Node Type ID\": \"42\", \"Total Cost\": 50983.400417, \"Plan Rows\": 1.0, \"Plans\": [{\"Node Type\": \"Seq Scan\", \"Node Type ID\": \"19\", \"Relation Name\": \"movie_keyword\", \"Total Cost\": 48016.135417, \"Plan Rows\": 1186902.0}]}]}]}, \"Buffers\": {\"title\": 12639, \"movie_keyword\": 484, \"cast_info\": 768, \"title_pkey\": 2167, \"movie_info_pkey\": 1, \"movie_info_idx_pkey\": 1, \"movie_info_idx\": 96, \"cast_info_pkey\": 1, \"movie_keyword_pkey\": 1, \"movie_info\": 96}}", 202.817658]