["{\"Plan\": {\"Node Type\": \"Other\", \"Node Type ID\": \"42\", \"Total Cost\": 1015023.430958, \"Plan Rows\": 1.0, \"Plans\": [{\"Node Type\": \"Other\", \"Node Type ID\": \"45\", \"Total Cost\": 1015023.415958, \"Plan Rows\": 2.0, \"Plans\": [{\"Node Type\": \"Other\", \"Node Type ID\": \"42\", \"Total Cost\": 1014023.215958, \"Plan Rows\": 1.0, \"Plans\": [{\"Node Type\": \"Hash Join\", \"Node Type ID\": \"38\", \"Total Cost\": 993200.758458, \"Plan Rows\": 8328979.0, \"Plans\": [{\"Node Type\": \"Seq Scan\", \"Node Type ID\": \"19\", \"Relation Name\": \"cast_info\", \"Total Cost\": 479184.525, \"Plan Rows\": 3605259.0}, {\"Node Type\": \"Other\", \"Node Type ID\": \"47\", \"Total Cost\": 383682.958458, \"Plan Rows\": 2433672.0, \"Plans\": [{\"Node Type\": \"Hash Join\", \"Node Type ID\": \"38\", \"Total Cost\": 383682.958458, \"Plan Rows\": 2433672.0, \"Plans\": [{\"Node Type\": \"Seq Scan\", \"Node Type ID\": \"19\", \"Relation Name\": \"movie_info\", \"Total Cost\": 283223.333333, \"Plan Rows\": 2433672.0}, {\"Node Type\": \"Other\", \"Node Type ID\": \"47\", \"Total Cost\": 53659.325, \"Plan Rows\": 1053432.0, \"Plans\": [{\"Node Type\": \"Seq Scan\", \"Node Type ID\": \"19\", \"Relation Name\": \"title\", \"Total Cost\": 53659.325, \"Plan Rows\": 1053432.0}]}]}]}]}]}]}]}, \"Buffers\": {\"title\": 13307, \"movie_companies\": 1091, \"movie_info_idx_pkey\": 1, \"movie_keyword_pkey\": 1, \"title_pkey\": 594, \"movie_keyword\": 1027, \"cast_info\": 192, \"cast_info_pkey\": 1, \"movie_companies_pkey\": 1, \"movie_info_idx\": 41}}", 7440.047451]