["{\"Plan\": {\"Node Type\": \"Other\", \"Node Type ID\": \"42\", \"Total Cost\": 108497.563208, \"Plan Rows\": 1.0, \"Plans\": [{\"Node Type\": \"Other\", \"Node Type ID\": \"45\", \"Total Cost\": 108497.548208, \"Plan Rows\": 2.0, \"Plans\": [{\"Node Type\": \"Other\", \"Node Type ID\": \"42\", \"Total Cost\": 107497.348208, \"Plan Rows\": 1.0, \"Plans\": [{\"Node Type\": \"Hash Join\", \"Node Type ID\": \"38\", \"Total Cost\": 107479.995708, \"Plan Rows\": 6937.0, \"Plans\": [{\"Node Type\": \"Seq Scan\", \"Node Type ID\": \"19\", \"Relation Name\": \"movie_info_idx\", \"Total Cost\": 15122.682292, \"Plan Rows\": 190138.0}, {\"Node Type\": \"Other\", \"Node Type ID\": \"47\", \"Total Cost\": 91135.008417, \"Plan Rows\": 38431.0, \"Plans\": [{\"Node Type\": \"Hash Join\", \"Node Type ID\": \"38\", \"Total Cost\": 91135.008417, \"Plan Rows\": 38431.0, \"Plans\": [{\"Node Type\": \"Seq Scan\", \"Node Type ID\": \"19\", \"Relation Name\": \"movie_companies\", \"Total Cost\": 32379.213542, \"Plan Rows\": 634329.0}, {\"Node Type\": \"Other\", \"Node Type ID\": \"47\", \"Total Cost\": 56292.90625, \"Plan Rows\": 63822.0, \"Plans\": [{\"Node Type\": \"Seq Scan\", \"Node Type ID\": \"19\", \"Relation Name\": \"title\", \"Total Cost\": 56292.90625, \"Plan Rows\": 63822.0}]}]}]}]}]}]}]}, \"Buffers\": {\"title\": 12237, \"movie_companies\": 192, \"title_pkey\": 3154, \"movie_keyword\": 192, \"movie_keyword_pkey\": 1, \"cast_info\": 284, \"movie_info\": 192, \"cast_info_pkey\": 1, \"movie_info_pkey\": 1, \"movie_companies_pkey\": 1}}", 462.878943]