["{\"Plan\": {\"Node Type\": \"Other\", \"Node Type ID\": \"42\", \"Total Cost\": 347648.026138, \"Plan Rows\": 1.0, \"Plans\": [{\"Node Type\": \"Other\", \"Node Type ID\": \"45\", \"Total Cost\": 347648.011138, \"Plan Rows\": 2.0, \"Plans\": [{\"Node Type\": \"Other\", \"Node Type ID\": \"42\", \"Total Cost\": 346647.811138, \"Plan Rows\": 1.0, \"Plans\": [{\"Node Type\": \"Hash Join\", \"Node Type ID\": \"38\", \"Total Cost\": 346647.096138, \"Plan Rows\": 282.0, \"Plans\": [{\"Node Type\": \"Seq Scan\", \"Node Type ID\": \"19\", \"Relation Name\": \"movie_info\", \"Total Cost\": 283223.333333, \"Plan Rows\": 3877365.0}, {\"Node Type\": \"Other\", \"Node Type ID\": \"47\", \"Total Cost\": 48881.501554, \"Plan Rows\": 77.0, \"Plans\": [{\"Node Type\": \"Nested Loop\", \"Node Type ID\": \"36\", \"Total Cost\": 48881.501554, \"Plan Rows\": 77.0, \"Plans\": [{\"Node Type\": \"Seq Scan\", \"Node Type ID\": \"19\", \"Relation Name\": \"movie_keyword\", \"Total Cost\": 48016.135417, \"Plan Rows\": 103.0}, {\"Node Type\": \"Index Scan\", \"Node Type ID\": \"21\", \"Relation Name\": \"title\", \"Total Cost\": 8.401613, \"Plan Rows\": 1.0}]}]}]}]}]}]}, \"Buffers\": {\"title\": 12796, \"movie_keyword\": 2177, \"title_pkey\": 550, \"cast_info\": 431, \"movie_info\": 192, \"movie_companies_pkey\": 1, \"cast_info_pkey\": 1, \"movie_keyword_pkey\": 1, \"movie_info_idx_pkey\": 1, \"movie_info_idx\": 96, \"movie_info_pkey\": 1}}", 1104.189775]