["{\"Plan\": {\"Node Type\": \"Other\", \"Node Type ID\": \"42\", \"Total Cost\": 705791.634208, \"Plan Rows\": 1.0, \"Plans\": [{\"Node Type\": \"Other\", \"Node Type ID\": \"45\", \"Total Cost\": 705791.619208, \"Plan Rows\": 2.0, \"Plans\": [{\"Node Type\": \"Other\", \"Node Type ID\": \"42\", \"Total Cost\": 704791.419208, \"Plan Rows\": 1.0, \"Plans\": [{\"Node Type\": \"Hash Join\", \"Node Type ID\": \"38\", \"Total Cost\": 697765.884208, \"Plan Rows\": 2810210.0, \"Plans\": [{\"Node Type\": \"Seq Scan\", \"Node Type ID\": \"19\", \"Relation Name\": \"cast_info\", \"Total Cost\": 403685.35, \"Plan Rows\": 15099835.0}, {\"Node Type\": \"Other\", \"Node Type ID\": \"47\", \"Total Cost\": 103796.280458, \"Plan Rows\": 196053.0, \"Plans\": [{\"Node Type\": \"Hash Join\", \"Node Type ID\": \"38\", \"Total Cost\": 103796.280458, \"Plan Rows\": 196053.0, \"Plans\": [{\"Node Type\": \"Seq Scan\", \"Node Type ID\": \"19\", \"Relation Name\": \"movie_companies\", \"Total Cost\": 29661.370833, \"Plan Rows\": 1087137.0}, {\"Node Type\": \"Other\", \"Node Type ID\": \"47\", \"Total Cost\": 58926.4875, \"Plan Rows\": 189975.0, \"Plans\": [{\"Node Type\": \"Seq Scan\", \"Node Type ID\": \"19\", \"Relation Name\": \"title\", \"Total Cost\": 58926.4875, \"Plan Rows\": 189975.0}]}]}]}]}]}]}]}, \"Buffers\": {\"title\": 14486, \"movie_keyword\": 421, \"title_pkey\": 36, \"movie_companies_pkey\": 1, \"cast_info_pkey\": 1, \"movie_info\": 192, \"cast_info\": 599, \"movie_keyword_pkey\": 1, \"movie_info_idx_pkey\": 1, \"movie_info_idx\": 192, \"movie_companies\": 292, \"movie_info_pkey\": 1}}", 5724.849844]