["{\"Plan\": {\"Node Type\": \"Other\", \"Node Type ID\": \"42\", \"Total Cost\": 60006.8425, \"Plan Rows\": 1.0, \"Plans\": [{\"Node Type\": \"Other\", \"Node Type ID\": \"45\", \"Total Cost\": 60006.8275, \"Plan Rows\": 2.0, \"Plans\": [{\"Node Type\": \"Other\", \"Node Type ID\": \"42\", \"Total Cost\": 59006.6275, \"Plan Rows\": 1.0, \"Plans\": [{\"Node Type\": \"Seq Scan\", \"Node Type ID\": \"19\", \"Relation Name\": \"title\", \"Total Cost\": 58926.4875, \"Plan Rows\": 32052.0}]}]}]}, \"Buffers\": {\"cast_info\": 1116, \"title\": 12966, \"movie_keyword\": 1583, \"title_pkey\": 15, \"movie_companies\": 457, \"movie_info_pkey\": 1, \"movie_keyword_pkey\": 1, \"cast_info_pkey\": 1, \"movie_companies_pkey\": 1, \"movie_info\": 96}}", 150.774387]