["{\"Plan\": {\"Node Type\": \"Other\", \"Node Type ID\": \"42\", \"Total Cost\": 80824.158988, \"Plan Rows\": 1.0, \"Plans\": [{\"Node Type\": \"Other\", \"Node Type ID\": \"45\", \"Total Cost\": 80824.143988, \"Plan Rows\": 2.0, \"Plans\": [{\"Node Type\": \"Other\", \"Node Type ID\": \"42\", \"Total Cost\": 79823.943988, \"Plan Rows\": 1.0, \"Plans\": [{\"Node Type\": \"Nested Loop\", \"Node Type ID\": \"36\", \"Total Cost\": 79820.823988, \"Plan Rows\": 1244.0, \"Plans\": [{\"Node Type\": \"Hash Join\", \"Node Type ID\": \"38\", \"Total Cost\": 73470.89, \"Plan Rows\": 10564.0, \"Plans\": [{\"Node Type\": \"Seq Scan\", \"Node Type ID\": \"19\", \"Relation Name\": \"movie_keyword\", \"Total Cost\": 48016.135417, \"Plan Rows\": 3707.0}, {\"Node Type\": \"Other\", \"Node Type ID\": \"47\", \"Total Cost\": 13685.145833, \"Plan Rows\": 575015.0, \"Plans\": [{\"Node Type\": \"Seq Scan\", \"Node Type ID\": \"19\", \"Relation Name\": \"movie_info_idx\", \"Total Cost\": 13685.145833, \"Plan Rows\": 575015.0}]}]}, {\"Node Type\": \"Index Scan\", \"Node Type ID\": \"21\", \"Relation Name\": \"title\", \"Total Cost\": 0.601092, \"Plan Rows\": 1.0}]}]}]}]}, \"Buffers\": {\"title\": 15534, \"movie_info\": 192, \"cast_info\": 288, \"movie_companies\": 119, \"movie_keyword\": 96, \"title_pkey\": 10, \"cast_info_pkey\": 1, \"movie_keyword_pkey\": 1, \"movie_info_pkey\": 1}}", 722.393666]