["{\"Plan\": {\"Node Type\": \"Other\", \"Node Type ID\": \"42\", \"Total Cost\": 50797.315417, \"Plan Rows\": 1.0, \"Plans\": [{\"Node Type\": \"Other\", \"Node Type ID\": \"45\", \"Total Cost\": 50797.300417, \"Plan Rows\": 2.0, \"Plans\": [{\"Node Type\": \"Other\", \"Node Type ID\": \"42\", \"Total Cost\": 49797.100417, \"Plan Rows\": 1.0, \"Plans\": [{\"Node Type\": \"Seq Scan\", \"Node Type ID\": \"19\", \"Relation Name\": \"movie_keyword\", \"Total Cost\": 48016.135417, \"Plan Rows\": 712382.0}]}]}]}, \"Buffers\": {\"title\": 11831, \"title_pkey\": 680, \"movie_info\": 696, \"movie_keyword\": 1406, \"movie_companies\": 1206, \"movie_companies_pkey\": 1, \"cast_info\": 317, \"cast_info_pkey\": 1, \"movie_info_idx\": 96, \"movie_info_pkey\": 1, \"movie_info_idx_pkey\": 1, \"movie_keyword_pkey\": 1}}", 196.842325]