["{\"Plan\": {\"Node Type\": \"Other\", \"Node Type ID\": \"42\", \"Total Cost\": 104244.16075, \"Plan Rows\": 1.0, \"Plans\": [{\"Node Type\": \"Other\", \"Node Type ID\": \"45\", \"Total Cost\": 104244.14575, \"Plan Rows\": 2.0, \"Plans\": [{\"Node Type\": \"Other\", \"Node Type ID\": \"42\", \"Total Cost\": 103243.94575, \"Plan Rows\": 1.0, \"Plans\": [{\"Node Type\": \"Hash Join\", \"Node Type ID\": \"38\", \"Total Cost\": 103050.59075, \"Plan Rows\": 77338.0, \"Plans\": [{\"Node Type\": \"Seq Scan\", \"Node Type ID\": \"19\", \"Relation Name\": \"movie_companies\", \"Total Cost\": 35097.05625, \"Plan Rows\": 263956.0}, {\"Node Type\": \"Other\", \"Node Type ID\": \"47\", \"Total Cost\": 58926.4875, \"Plan Rows\": 308653.0, \"Plans\": [{\"Node Type\": \"Seq Scan\", \"Node Type ID\": \"19\", \"Relation Name\": \"title\", \"Total Cost\": 58926.4875, \"Plan Rows\": 308653.0}]}]}]}]}]}, \"Buffers\": {\"title\": 14197, \"cast_info\": 679, \"movie_keyword\": 293, \"title_pkey\": 488, \"movie_info_idx\": 383, \"movie_companies_pkey\": 1, \"movie_companies\": 192, \"cast_info_pkey\": 1, \"movie_keyword_pkey\": 1, \"movie_info_idx_pkey\": 1, \"movie_info_pkey\": 1}}", 616.376702]