["{\"Plan\": {\"Node Type\": \"Other\", \"Node Type ID\": \"42\", \"Total Cost\": 823028.438208, \"Plan Rows\": 1.0, \"Plans\": [{\"Node Type\": \"Other\", \"Node Type ID\": \"45\", \"Total Cost\": 823028.423208, \"Plan Rows\": 2.0, \"Plans\": [{\"Node Type\": \"Other\", \"Node Type ID\": \"42\", \"Total Cost\": 822028.223208, \"Plan Rows\": 1.0, \"Plans\": [{\"Node Type\": \"Hash Join\", \"Node Type ID\": \"38\", \"Total Cost\": 821843.788208, \"Plan Rows\": 73770.0, \"Plans\": [{\"Node Type\": \"Seq Scan\", \"Node Type ID\": \"19\", \"Relation Name\": \"movie_info\", \"Total Cost\": 283223.333333, \"Plan Rows\": 272146.0}, {\"Node Type\": \"Other\", \"Node Type ID\": \"47\", \"Total Cost\": 528002.419875, \"Plan Rows\": 285551.0, \"Plans\": [{\"Node Type\": \"Hash Join\", \"Node Type ID\": \"38\", \"Total Cost\": 528002.419875, \"Plan Rows\": 285551.0, \"Plans\": [{\"Node Type\": \"Seq Scan\", \"Node Type ID\": \"19\", \"Relation Name\": \"cast_info\", \"Total Cost\": 441434.9375, \"Plan Rows\": 11407584.0}, {\"Node Type\": \"Other\", \"Node Type ID\": \"47\", \"Total Cost\": 56292.90625, \"Plan Rows\": 26369.0, \"Plans\": [{\"Node Type\": \"Seq Scan\", \"Node Type ID\": \"19\", \"Relation Name\": \"title\", \"Total Cost\": 56292.90625, \"Plan Rows\": 26369.0}]}]}]}]}]}]}]}, \"Buffers\": {\"title\": 12760, \"cast_info\": 679, \"movie_keyword\": 1911, \"movie_companies_pkey\": 1, \"title_pkey\": 506, \"movie_companies\": 189, \"movie_info_pkey\": 1, \"movie_keyword_pkey\": 1, \"cast_info_pkey\": 1, \"movie_info_idx_pkey\": 1, \"movie_info_idx\": 96, \"movie_info\": 96}}", 3892.355676]