["{\"Plan\": {\"Node Type\": \"Other\", \"Node Type ID\": \"42\", \"Total Cost\": 163268.006042, \"Plan Rows\": 1.0, \"Plans\": [{\"Node Type\": \"Other\", \"Node Type ID\": \"45\", \"Total Cost\": 163267.991042, \"Plan Rows\": 2.0, \"Plans\": [{\"Node Type\": \"Other\", \"Node Type ID\": \"42\", \"Total Cost\": 162267.791042, \"Plan Rows\": 1.0, \"Plans\": [{\"Node Type\": \"Hash Join\", \"Node Type ID\": \"38\", \"Total Cost\": 158059.503542, \"Plan Rows\": 1683311.0, \"Plans\": [{\"Node Type\": \"Seq Scan\", \"Node Type ID\": \"19\", \"Relation Name\": \"movie_keyword\", \"Total Cost\": 43303.708333, \"Plan Rows\": 1884971.0}, {\"Node Type\": \"Other\", \"Node Type ID\": \"47\", \"Total Cost\": 87955.178958, \"Plan Rows\": 180198.0, \"Plans\": [{\"Node Type\": \"Hash Join\", \"Node Type ID\": \"38\", \"Total Cost\": 87955.178958, \"Plan Rows\": 180198.0, \"Plans\": [{\"Node Type\": \"Seq Scan\", \"Node Type ID\": \"19\", \"Relation Name\": \"movie_info_idx\", \"Total Cost\": 13685.145833, \"Plan Rows\": 575015.0}, {\"Node Type\": \"Other\", \"Node Type ID\": \"47\", \"Total Cost\": 61560.06875, \"Plan Rows\": 330124.0, \"Plans\": [{\"Node Type\": \"Seq Scan\", \"Node Type ID\": \"19\", \"Relation Name\": \"title\", \"Total Cost\": 61560.06875, \"Plan Rows\": 330124.0}]}]}]}]}]}]}]}, \"Buffers\": {\"title\": 15573, \"movie_keyword\": 362, \"movie_companies_pkey\": 1, \"movie_info\": 105, \"movie_keyword_pkey\": 1, \"movie_info_idx\": 191, \"movie_info_idx_pkey\": 1, \"title_pkey\": 6}}", 1522.753522]