["{\"Plan\": {\"Node Type\": \"Other\", \"Node Type ID\": \"42\", \"Total Cost\": 405296.478958, \"Plan Rows\": 1.0, \"Plans\": [{\"Node Type\": \"Other\", \"Node Type ID\": \"45\", \"Total Cost\": 405296.463958, \"Plan Rows\": 2.0, \"Plans\": [{\"Node Type\": \"Other\", \"Node Type ID\": \"42\", \"Total Cost\": 404296.263958, \"Plan Rows\": 1.0, \"Plans\": [{\"Node Type\": \"Hash Join\", \"Node Type ID\": \"38\", \"Total Cost\": 403509.303958, \"Plan Rows\": 314780.0, \"Plans\": [{\"Node Type\": \"Seq Scan\", \"Node Type ID\": \"19\", \"Relation Name\": \"movie_keyword\", \"Total Cost\": 48016.135417, \"Plan Rows\": 1884818.0}, {\"Node Type\": \"Other\", \"Node Type ID\": \"47\", \"Total Cost\": 345604.986042, \"Plan Rows\": 23257.0, \"Plans\": [{\"Node Type\": \"Hash Join\", \"Node Type ID\": \"38\", \"Total Cost\": 345604.986042, \"Plan Rows\": 23257.0, \"Plans\": [{\"Node Type\": \"Seq Scan\", \"Node Type ID\": \"19\", \"Relation Name\": \"movie_info\", \"Total Cost\": 267783.866667, \"Plan Rows\": 6175787.0}, {\"Node Type\": \"Other\", \"Node Type ID\": \"47\", \"Total Cost\": 61560.06875, \"Plan Rows\": 3967.0, \"Plans\": [{\"Node Type\": \"Seq Scan\", \"Node Type ID\": \"19\", \"Relation Name\": \"title\", \"Total Cost\": 61560.06875, \"Plan Rows\": 3967.0}]}]}]}]}]}]}]}, \"Buffers\": {\"title\": 14451, \"movie_info\": 457, \"movie_keyword\": 976, \"title_pkey\": 253, \"movie_info_pkey\": 1, \"movie_companies_pkey\": 1, \"movie_keyword_pkey\": 1, \"movie_companies\": 78}}", 1603.387451]