["{\"Plan\": {\"Node Type\": \"Other\", \"Node Type ID\": \"42\", \"Total Cost\": 411503.6225, \"Plan Rows\": 1.0, \"Plans\": [{\"Node Type\": \"Other\", \"Node Type ID\": \"45\", \"Total Cost\": 411503.6075, \"Plan Rows\": 2.0, \"Plans\": [{\"Node Type\": \"Other\", \"Node Type ID\": \"42\", \"Total Cost\": 410503.4075, \"Plan Rows\": 1.0, \"Plans\": [{\"Node Type\": \"Hash Join\", \"Node Type ID\": \"38\", \"Total Cost\": 403520.635, \"Plan Rows\": 2793105.0, \"Plans\": [{\"Node Type\": \"Seq Scan\", \"Node Type ID\": \"19\", \"Relation Name\": \"movie_info\", \"Total Cost\": 267783.866667, \"Plan Rows\": 6175787.0}, {\"Node Type\": \"Other\", \"Node Type ID\": \"47\", \"Total Cost\": 110251.812083, \"Plan Rows\": 62982.0, \"Plans\": [{\"Node Type\": \"Hash Join\", \"Node Type ID\": \"38\", \"Total Cost\": 110251.812083, \"Plan Rows\": 62982.0, \"Plans\": [{\"Node Type\": \"Seq Scan\", \"Node Type ID\": \"19\", \"Relation Name\": \"movie_keyword\", \"Total Cost\": 43303.708333, \"Plan Rows\": 1884971.0}, {\"Node Type\": \"Other\", \"Node Type ID\": \"47\", \"Total Cost\": 61560.06875, \"Plan Rows\": 35198.0, \"Plans\": [{\"Node Type\": \"Seq Scan\", \"Node Type ID\": \"19\", \"Relation Name\": \"title\", \"Total Cost\": 61560.06875, \"Plan Rows\": 35198.0}]}]}]}]}]}]}]}, \"Buffers\": {\"title\": 13580, \"movie_keyword\": 896, \"movie_companies\": 911, \"movie_info_idx\": 384, \"movie_info_pkey\": 1, \"movie_info\": 192, \"movie_info_idx_pkey\": 1, \"movie_companies_pkey\": 1, \"title_pkey\": 252, \"movie_keyword_pkey\": 1}}", 1311.577214]