["{\"Plan\": {\"Node Type\": \"Other\", \"Node Type ID\": \"42\", \"Total Cost\": 113721.139208, \"Plan Rows\": 1.0, \"Plans\": [{\"Node Type\": \"Other\", \"Node Type ID\": \"45\", \"Total Cost\": 113721.124208, \"Plan Rows\": 2.0, \"Plans\": [{\"Node Type\": \"Other\", \"Node Type ID\": \"42\", \"Total Cost\": 112720.924208, \"Plan Rows\": 1.0, \"Plans\": [{\"Node Type\": \"Hash Join\", \"Node Type ID\": \"38\", \"Total Cost\": 112711.414208, \"Plan Rows\": 3800.0, \"Plans\": [{\"Node Type\": \"Seq Scan\", \"Node Type ID\": \"19\", \"Relation Name\": \"movie_companies\", \"Total Cost\": 32379.213542, \"Plan Rows\": 556288.0}, {\"Node Type\": \"Other\", \"Node Type ID\": \"47\", \"Total Cost\": 78224.963167, \"Plan Rows\": 1439.0, \"Plans\": [{\"Node Type\": \"Hash Join\", \"Node Type ID\": \"38\", \"Total Cost\": 78224.963167, \"Plan Rows\": 1439.0, \"Plans\": [{\"Node Type\": \"Seq Scan\", \"Node Type ID\": \"19\", \"Relation Name\": \"movie_info_idx\", \"Total Cost\": 15122.682292, \"Plan Rows\": 574957.0}, {\"Node Type\": \"Other\", \"Node Type ID\": \"47\", \"Total Cost\": 61560.06875, \"Plan Rows\": 2636.0, \"Plans\": [{\"Node Type\": \"Seq Scan\", \"Node Type ID\": \"19\", \"Relation Name\": \"title\", \"Total Cost\": 61560.06875, \"Plan Rows\": 2636.0}]}]}]}]}]}]}]}, \"Buffers\": {\"title\": 13777, \"movie_keyword\": 195, \"title_pkey\": 1952, \"movie_companies\": 313, \"movie_keyword_pkey\": 1, \"movie_companies_pkey\": 1}}", 585.484326]