["{\"Plan\": {\"Node Type\": \"Other\", \"Node Type ID\": \"42\", \"Total Cost\": 384861.182125, \"Plan Rows\": 1.0, \"Plans\": [{\"Node Type\": \"Other\", \"Node Type ID\": \"45\", \"Total Cost\": 384861.167125, \"Plan Rows\": 2.0, \"Plans\": [{\"Node Type\": \"Other\", \"Node Type ID\": \"42\", \"Total Cost\": 383860.967125, \"Plan Rows\": 1.0, \"Plans\": [{\"Node Type\": \"Hash Join\", \"Node Type ID\": \"38\", \"Total Cost\": 381398.382125, \"Plan Rows\": 985030.0, \"Plans\": [{\"Node Type\": \"Seq Scan\", \"Node Type ID\": \"19\", \"Relation Name\": \"movie_info\", \"Total Cost\": 267783.866667, \"Plan Rows\": 6175787.0}, {\"Node Type\": \"Other\", \"Node Type ID\": \"47\", \"Total Cost\": 89214.886708, \"Plan Rows\": 33591.0, \"Plans\": [{\"Node Type\": \"Hash Join\", \"Node Type ID\": \"38\", \"Total Cost\": 89214.886708, \"Plan Rows\": 33591.0, \"Plans\": [{\"Node Type\": \"Seq Scan\", \"Node Type ID\": \"19\", \"Relation Name\": \"movie_companies\", \"Total Cost\": 29661.370833, \"Plan Rows\": 1087137.0}, {\"Node Type\": \"Other\", \"Node Type ID\": \"47\", \"Total Cost\": 56292.90625, \"Plan Rows\": 32550.0, \"Plans\": [{\"Node Type\": \"Seq Scan\", \"Node Type ID\": \"19\", \"Relation Name\": \"title\", \"Total Cost\": 56292.90625, \"Plan Rows\": 32550.0}]}]}]}]}]}]}]}, \"Buffers\": {\"title_pkey\": 2672, \"title\": 12212, \"movie_info_idx\": 192, \"movie_companies\": 341, \"movie_keyword\": 462, \"movie_info_pkey\": 1, \"cast_info\": 96, \"movie_info\": 192, \"movie_info_idx_pkey\": 1, \"movie_companies_pkey\": 1, \"cast_info_pkey\": 1, \"movie_keyword_pkey\": 1}}", 2219.741929]