["{\"Plan\": {\"Node Type\": \"Other\", \"Node Type ID\": \"42\", \"Total Cost\": 406218.163958, \"Plan Rows\": 1.0, \"Plans\": [{\"Node Type\": \"Other\", \"Node Type ID\": \"45\", \"Total Cost\": 406218.148958, \"Plan Rows\": 2.0, \"Plans\": [{\"Node Type\": \"Other\", \"Node Type ID\": \"42\", \"Total Cost\": 405217.948958, \"Plan Rows\": 1.0, \"Plans\": [{\"Node Type\": \"Hash Join\", \"Node Type ID\": \"38\", \"Total Cost\": 403873.323958, \"Plan Rows\": 537846.0, \"Plans\": [{\"Node Type\": \"Seq Scan\", \"Node Type ID\": \"19\", \"Relation Name\": \"movie_keyword\", \"Total Cost\": 48016.135417, \"Plan Rows\": 1884818.0}, {\"Node Type\": \"Other\", \"Node Type ID\": \"47\", \"Total Cost\": 345640.123542, \"Plan Rows\": 39738.0, \"Plans\": [{\"Node Type\": \"Hash Join\", \"Node Type ID\": \"38\", \"Total Cost\": 345640.123542, \"Plan Rows\": 39738.0, \"Plans\": [{\"Node Type\": \"Seq Scan\", \"Node Type ID\": \"19\", \"Relation Name\": \"movie_info\", \"Total Cost\": 267783.866667, \"Plan Rows\": 6175787.0}, {\"Node Type\": \"Other\", \"Node Type ID\": \"47\", \"Total Cost\": 61560.06875, \"Plan Rows\": 6778.0, \"Plans\": [{\"Node Type\": \"Seq Scan\", \"Node Type ID\": \"19\", \"Relation Name\": \"title\", \"Total Cost\": 61560.06875, \"Plan Rows\": 6778.0}]}]}]}]}]}]}]}, \"Buffers\": {\"title\": 12888, \"movie_companies\": 447, \"title_pkey\": 1909, \"movie_keyword\": 376, \"movie_info\": 196, \"movie_info_idx\": 384, \"movie_keyword_pkey\": 1, \"movie_info_idx_pkey\": 1, \"movie_companies_pkey\": 1, \"movie_info_pkey\": 1}}", 1423.825304]