["{\"Plan\": {\"Node Type\": \"Other\", \"Node Type ID\": \"42\", \"Total Cost\": 145186.499167, \"Plan Rows\": 1.0, \"Plans\": [{\"Node Type\": \"Other\", \"Node Type ID\": \"45\", \"Total Cost\": 145186.484167, \"Plan Rows\": 2.0, \"Plans\": [{\"Node Type\": \"Other\", \"Node Type ID\": \"42\", \"Total Cost\": 144186.284167, \"Plan Rows\": 1.0, \"Plans\": [{\"Node Type\": \"Hash Join\", \"Node Type ID\": \"38\", \"Total Cost\": 143962.466667, \"Plan Rows\": 89523.0, \"Plans\": [{\"Node Type\": \"Seq Scan\", \"Node Type ID\": \"19\", \"Relation Name\": \"movie_companies\", \"Total Cost\": 29661.370833, \"Plan Rows\": 1087137.0}, {\"Node Type\": \"Other\", \"Node Type ID\": \"47\", \"Total Cost\": 109932.987083, \"Plan Rows\": 17342.0, \"Plans\": [{\"Node Type\": \"Hash Join\", \"Node Type ID\": \"38\", \"Total Cost\": 109932.987083, \"Plan Rows\": 17342.0, \"Plans\": [{\"Node Type\": \"Seq Scan\", \"Node Type ID\": \"19\", \"Relation Name\": \"movie_keyword\", \"Total Cost\": 43303.708333, \"Plan Rows\": 1884971.0}, {\"Node Type\": \"Other\", \"Node Type ID\": \"47\", \"Total Cost\": 61560.06875, \"Plan Rows\": 9692.0, \"Plans\": [{\"Node Type\": \"Seq Scan\", \"Node Type ID\": \"19\", \"Relation Name\": \"title\", \"Total Cost\": 61560.06875, \"Plan Rows\": 9692.0}]}]}]}]}]}]}]}, \"Buffers\": {\"title\": 13955, \"movie_companies\": 1056, \"movie_keyword\": 357, \"movie_info_idx\": 146, \"title_pkey\": 532, \"movie_keyword_pkey\": 1, \"movie_info\": 192, \"movie_companies_pkey\": 1}}", 483.291628]