["{\"Plan\": {\"Node Type\": \"Other\", \"Node Type ID\": \"42\", \"Total Cost\": 50175.977758, \"Plan Rows\": 1.0, \"Plans\": [{\"Node Type\": \"Other\", \"Node Type ID\": \"45\", \"Total Cost\": 50175.962758, \"Plan Rows\": 2.0, \"Plans\": [{\"Node Type\": \"Other\", \"Node Type ID\": \"42\", \"Total Cost\": 49175.762758, \"Plan Rows\": 1.0, \"Plans\": [{\"Node Type\": \"Nested Loop\", \"Node Type ID\": \"36\", \"Total Cost\": 49174.285258, \"Plan Rows\": 587.0, \"Plans\": [{\"Node Type\": \"Hash Join\", \"Node Type ID\": \"38\", \"Total Cost\": 48864.691875, \"Plan Rows\": 587.0, \"Plans\": [{\"Node Type\": \"Seq Scan\", \"Node Type ID\": \"19\", \"Relation Name\": \"movie_companies\", \"Total Cost\": 29661.370833, \"Plan Rows\": 1087137.0}, {\"Node Type\": \"Other\", \"Node Type ID\": \"47\", \"Total Cost\": 15122.682292, \"Plan Rows\": 114.0, \"Plans\": [{\"Node Type\": \"Seq Scan\", \"Node Type ID\": \"19\", \"Relation Name\": \"movie_info_idx\", \"Total Cost\": 15122.682292, \"Plan Rows\": 114.0}]}]}, {\"Node Type\": \"Index Only Scan\", \"Node Type ID\": \"22\", \"Relation Name\": \"title\", \"Total Cost\": 0.527416, \"Plan Rows\": 1.0}]}]}]}]}, \"Buffers\": {\"movie_keyword\": 776, \"title\": 15083, \"movie_info\": 192, \"title_pkey\": 6, \"movie_keyword_pkey\": 1, \"movie_info_idx_pkey\": 1, \"movie_info_pkey\": 1, \"movie_companies\": 96}}", 173.193922]