["{\"Plan\": {\"Node Type\": \"Other\", \"Node Type ID\": \"42\", \"Total Cost\": 425001.506667, \"Plan Rows\": 1.0, \"Plans\": [{\"Node Type\": \"Other\", \"Node Type ID\": \"45\", \"Total Cost\": 425001.491667, \"Plan Rows\": 2.0, \"Plans\": [{\"Node Type\": \"Other\", \"Node Type ID\": \"42\", \"Total Cost\": 424001.291667, \"Plan Rows\": 1.0, \"Plans\": [{\"Node Type\": \"Hash Join\", \"Node Type ID\": \"38\", \"Total Cost\": 418962.476667, \"Plan Rows\": 2015522.0, \"Plans\": [{\"Node Type\": \"Seq Scan\", \"Node Type ID\": \"19\", \"Relation Name\": \"movie_info\", \"Total Cost\": 283223.333333, \"Plan Rows\": 5657844.0}, {\"Node Type\": \"Other\", \"Node Type ID\": \"47\", \"Total Cost\": 112791.968333, \"Plan Rows\": 49608.0, \"Plans\": [{\"Node Type\": \"Hash Join\", \"Node Type ID\": \"38\", \"Total Cost\": 112791.968333, \"Plan Rows\": 49608.0, \"Plans\": [{\"Node Type\": \"Seq Scan\", \"Node Type ID\": \"19\", \"Relation Name\": \"movie_keyword\", \"Total Cost\": 43303.708333, \"Plan Rows\": 1884971.0}, {\"Node Type\": \"Other\", \"Node Type ID\": \"47\", \"Total Cost\": 64193.65, \"Plan Rows\": 27724.0, \"Plans\": [{\"Node Type\": \"Seq Scan\", \"Node Type ID\": \"19\", \"Relation Name\": \"title\", \"Total Cost\": 64193.65, \"Plan Rows\": 27724.0}]}]}]}]}]}]}]}, \"Buffers\": {\"title\": 15001, \"movie_companies\": 245, \"movie_keyword\": 661, \"title_pkey\": 6, \"movie_keyword_pkey\": 1, \"movie_info_pkey\": 1, \"movie_companies_pkey\": 1, \"movie_info_idx_pkey\": 1, \"movie_info\": 96, \"movie_info_idx\": 192}}", 1615.049707]