["{\"Plan\": {\"Node Type\": \"Other\", \"Node Type ID\": \"42\", \"Total Cost\": 114386.004, \"Plan Rows\": 1.0, \"Plans\": [{\"Node Type\": \"Other\", \"Node Type ID\": \"45\", \"Total Cost\": 114385.989, \"Plan Rows\": 2.0, \"Plans\": [{\"Node Type\": \"Other\", \"Node Type ID\": \"42\", \"Total Cost\": 113385.789, \"Plan Rows\": 1.0, \"Plans\": [{\"Node Type\": \"Hash Join\", \"Node Type ID\": \"38\", \"Total Cost\": 113369.254, \"Plan Rows\": 6610.0, \"Plans\": [{\"Node Type\": \"Seq Scan\", \"Node Type ID\": \"19\", \"Relation Name\": \"movie_info_idx\", \"Total Cost\": 15122.682292, \"Plan Rows\": 384875.0}, {\"Node Type\": \"Other\", \"Node Type ID\": \"47\", \"Total Cost\": 96752.567958, \"Plan Rows\": 3617.0, \"Plans\": [{\"Node Type\": \"Hash Join\", \"Node Type ID\": \"38\", \"Total Cost\": 96752.567958, \"Plan Rows\": 3617.0, \"Plans\": [{\"Node Type\": \"Seq Scan\", \"Node Type ID\": \"19\", \"Relation Name\": \"movie_companies\", \"Total Cost\": 29661.370833, \"Plan Rows\": 1087137.0}, {\"Node Type\": \"Other\", \"Node Type ID\": \"47\", \"Total Cost\": 64193.65, \"Plan Rows\": 3505.0, \"Plans\": [{\"Node Type\": \"Seq Scan\", \"Node Type ID\": \"19\", \"Relation Name\": \"title\", \"Total Cost\": 64193.65, \"Plan Rows\": 3505.0}]}]}]}]}]}]}]}, \"Buffers\": {\"title\": 14981, \"movie_companies\": 877, \"movie_keyword_pkey\": 1, \"movie_companies_pkey\": 1, \"movie_info_idx\": 288, \"movie_info_pkey\": 1, \"movie_info\": 96, \"title_pkey\": 6}}", 384.172497]