["{\"Plan\": {\"Node Type\": \"Other\", \"Node Type ID\": \"42\", \"Total Cost\": 454652.657458, \"Plan Rows\": 1.0, \"Plans\": [{\"Node Type\": \"Other\", \"Node Type ID\": \"45\", \"Total Cost\": 454652.642458, \"Plan Rows\": 2.0, \"Plans\": [{\"Node Type\": \"Other\", \"Node Type ID\": \"42\", \"Total Cost\": 453652.442458, \"Plan Rows\": 1.0, \"Plans\": [{\"Node Type\": \"Hash Join\", \"Node Type ID\": \"38\", \"Total Cost\": 445527.257458, \"Plan Rows\": 3250070.0, \"Plans\": [{\"Node Type\": \"Seq Scan\", \"Node Type ID\": \"19\", \"Relation Name\": \"movie_info\", \"Total Cost\": 267783.866667, \"Plan Rows\": 6175787.0}, {\"Node Type\": \"Other\", \"Node Type ID\": \"47\", \"Total Cost\": 101375.469542, \"Plan Rows\": 110832.0, \"Plans\": [{\"Node Type\": \"Hash Join\", \"Node Type ID\": \"38\", \"Total Cost\": 101375.469542, \"Plan Rows\": 110832.0, \"Plans\": [{\"Node Type\": \"Seq Scan\", \"Node Type ID\": \"19\", \"Relation Name\": \"movie_companies\", \"Total Cost\": 32379.213542, \"Plan Rows\": 556288.0}, {\"Node Type\": \"Other\", \"Node Type ID\": \"47\", \"Total Cost\": 58926.4875, \"Plan Rows\": 209881.0, \"Plans\": [{\"Node Type\": \"Seq Scan\", \"Node Type ID\": \"19\", \"Relation Name\": \"title\", \"Total Cost\": 58926.4875, \"Plan Rows\": 209881.0}]}]}]}]}]}]}]}, \"Buffers\": {\"title\": 14266, \"movie_keyword\": 1343, \"title_pkey\": 6, \"movie_info_idx\": 410, \"movie_companies\": 126, \"movie_companies_pkey\": 1, \"cast_info_pkey\": 1, \"cast_info\": 96, \"movie_info_idx_pkey\": 1, \"movie_keyword_pkey\": 1}}", 3252.874691]