["{\"Plan\": {\"Node Type\": \"Other\", \"Node Type ID\": \"42\", \"Total Cost\": 641875.252958, \"Plan Rows\": 1.0, \"Plans\": [{\"Node Type\": \"Other\", \"Node Type ID\": \"45\", \"Total Cost\": 641875.237958, \"Plan Rows\": 2.0, \"Plans\": [{\"Node Type\": \"Other\", \"Node Type ID\": \"42\", \"Total Cost\": 640875.037958, \"Plan Rows\": 1.0, \"Plans\": [{\"Node Type\": \"Hash Join\", \"Node Type ID\": \"38\", \"Total Cost\": 522876.820458, \"Plan Rows\": 47199283.0, \"Plans\": [{\"Node Type\": \"Seq Scan\", \"Node Type ID\": \"19\", \"Relation Name\": \"movie_info\", \"Total Cost\": 267783.866667, \"Plan Rows\": 6175787.0}, {\"Node Type\": \"Other\", \"Node Type ID\": \"47\", \"Total Cost\": 136066.200042, \"Plan Rows\": 1064297.0, \"Plans\": [{\"Node Type\": \"Hash Join\", \"Node Type ID\": \"38\", \"Total Cost\": 136066.200042, \"Plan Rows\": 1064297.0, \"Plans\": [{\"Node Type\": \"Seq Scan\", \"Node Type ID\": \"19\", \"Relation Name\": \"movie_keyword\", \"Total Cost\": 48016.135417, \"Plan Rows\": 1884818.0}, {\"Node Type\": \"Other\", \"Node Type ID\": \"47\", \"Total Cost\": 56292.90625, \"Plan Rows\": 594840.0, \"Plans\": [{\"Node Type\": \"Seq Scan\", \"Node Type ID\": \"19\", \"Relation Name\": \"title\", \"Total Cost\": 56292.90625, \"Plan Rows\": 594840.0}]}]}]}]}]}]}]}, \"Buffers\": {\"title\": 13974, \"movie_keyword\": 1000, \"movie_keyword_pkey\": 1, \"movie_info_idx\": 510, \"title_pkey\": 6, \"movie_companies\": 663, \"movie_info\": 96, \"movie_companies_pkey\": 1, \"movie_info_idx_pkey\": 1}}", 12580.671481]