["{\"Plan\": {\"Node Type\": \"Other\", \"Node Type ID\": \"42\", \"Total Cost\": 110868.483208, \"Plan Rows\": 1.0, \"Plans\": [{\"Node Type\": \"Other\", \"Node Type ID\": \"45\", \"Total Cost\": 110868.468208, \"Plan Rows\": 2.0, \"Plans\": [{\"Node Type\": \"Other\", \"Node Type ID\": \"42\", \"Total Cost\": 109868.268208, \"Plan Rows\": 1.0, \"Plans\": [{\"Node Type\": \"Hash Join\", \"Node Type ID\": \"38\", \"Total Cost\": 109804.730708, \"Plan Rows\": 25411.0, \"Plans\": [{\"Node Type\": \"Seq Scan\", \"Node Type ID\": \"19\", \"Relation Name\": \"movie_info_idx\", \"Total Cost\": 15122.682292, \"Plan Rows\": 384743.0}, {\"Node Type\": \"Other\", \"Node Type ID\": \"47\", \"Total Cost\": 93044.217167, \"Plan Rows\": 13910.0, \"Plans\": [{\"Node Type\": \"Hash Join\", \"Node Type ID\": \"38\", \"Total Cost\": 93044.217167, \"Plan Rows\": 13910.0, \"Plans\": [{\"Node Type\": \"Seq Scan\", \"Node Type ID\": \"19\", \"Relation Name\": \"movie_companies\", \"Total Cost\": 32379.213542, \"Plan Rows\": 530849.0}, {\"Node Type\": \"Other\", \"Node Type ID\": \"47\", \"Total Cost\": 58926.4875, \"Plan Rows\": 27603.0, \"Plans\": [{\"Node Type\": \"Seq Scan\", \"Node Type ID\": \"19\", \"Relation Name\": \"title\", \"Total Cost\": 58926.4875, \"Plan Rows\": 27603.0}]}]}]}]}]}]}]}, \"Buffers\": {\"title\": 14295, \"movie_companies\": 1056, \"movie_info_idx\": 302, \"title_pkey\": 280, \"movie_keyword\": 192, \"movie_info_pkey\": 1, \"movie_info\": 96, \"movie_keyword_pkey\": 1, \"movie_info_idx_pkey\": 1, \"movie_companies_pkey\": 1}}", 471.152693]