["{\"Plan\": {\"Node Type\": \"Other\", \"Node Type ID\": \"42\", \"Total Cost\": 9982.275551, \"Plan Rows\": 1.0, \"Plans\": [{\"Node Type\": \"Other\", \"Node Type ID\": \"45\", \"Total Cost\": 9982.263051, \"Plan Rows\": 1.0, \"Plans\": [{\"Node Type\": \"Other\", \"Node Type ID\": \"42\", \"Total Cost\": 8982.163051, \"Plan Rows\": 1.0, \"Plans\": [{\"Node Type\": \"Nested Loop\", \"Node Type ID\": \"36\", \"Total Cost\": 8824.158051, \"Plan Rows\": 63198.0, \"Plans\": [{\"Node Type\": \"Nested Loop\", \"Node Type ID\": \"36\", \"Total Cost\": 7928.867906, \"Plan Rows\": 1894.0, \"Plans\": [{\"Node Type\": \"Nested Loop\", \"Node Type ID\": \"36\", \"Total Cost\": 7520.242832, \"Plan Rows\": 636.0, \"Plans\": [{\"Node Type\": \"Nested Loop\", \"Node Type ID\": \"36\", \"Total Cost\": 7276.774206, \"Plan Rows\": 336.0, \"Plans\": [{\"Node Type\": \"Nested Loop\", \"Node Type ID\": \"36\", \"Total Cost\": 7142.508918, \"Plan Rows\": 369.0, \"Plans\": [{\"Node Type\": \"Seq Scan\", \"Node Type ID\": \"19\", \"Relation Name\": \"votes\", \"Total Cost\": 4542.235294, \"Plan Rows\": 805.0}, {\"Node Type\": \"Index Scan\", \"Node Type ID\": \"21\", \"Relation Name\": \"posts\", \"Total Cost\": 3.230153, \"Plan Rows\": 1.0}]}, {\"Node Type\": \"Index Scan\", \"Node Type ID\": \"21\", \"Relation Name\": \"users\", \"Total Cost\": 0.363863, \"Plan Rows\": 1.0}]}, {\"Node Type\": \"Index Only Scan\", \"Node Type ID\": \"22\", \"Relation Name\": \"comments\", \"Total Cost\": 0.674609, \"Plan Rows\": 5.0}]}, {\"Node Type\": \"Index Scan\", \"Node Type ID\": \"21\", \"Relation Name\": \"posthistory\", \"Total Cost\": 0.592492, \"Plan Rows\": 4.0}]}, {\"Node Type\": \"Index Only Scan\", \"Node Type ID\": \"22\", \"Relation Name\": \"badges\", \"Total Cost\": 0.432698, \"Plan Rows\": 4.0}]}]}]}]}, \"Buffers\": {\"comments_pkey\": 1, \"idx_comments_postid\": 482, \"idx_comments_userid\": 475, \"posthistory_pkey\": 1, \"idx_posthistory_postid\": 835, \"idx_posthistory_userid\": 835, \"badges_pkey\": 1, \"idx_badges_userid\": 221, \"users_pkey\": 113, \"comments\": 1281, \"posthistory\": 2215, \"badges\": 432, \"users\": 297, \"votes_pkey\": 1, \"idx_votes_userid\": 900, \"idx_votes_postid\": 900, \"posts_pkey\": 254, \"idx_posts_owneruserid\": 252, \"idx_posts_lasteditoruserid\": 1, \"votes\": 2130, \"posts\": 810, \"postlinks_pkey\": 1, \"idx_postlinks_relatedpostid\": 33, \"idx_postlinks_postid\": 33, \"postlinks\": 82, \"tags_pkey\": 1, \"idx_tags_excerptpostid\": 4, \"tags\": 6}}", 41.20872]